{
    "minVersion": "0.1",
	 "headerImage": "https://imod668.github.io/header.png",
	 "tintColor": "",
    "tabs": [
      {
        "tabname": "Details",
        "views": [
          {
            "itemCornerRadius": 4,
            "itemSize": "{187.5, 333.5}",
            "screenshots": [
              {
                "accessibilityText": "Screenshot",
                "url": "https://imod668.github.io/depictions/com.tweak.slyd/1.jpg"
              },
			  {
                "accessibilityText": "Screenshot",
                "url": "https://imod668.github.io/depictions/com.tweak.slyd/2.jpg"
              },
            ],
            "class": "DepictionScreenshotsView"
          },
          {
            "markdown": "Slide to unlock for iOS 11 and 12.",
            "useSpacing": true,
            "class": "DepictionMarkdownView"
          },
          {
            "class": "DepictionSeparatorView"
          },
          {
            "title": "Information",
            "class": "DepictionHeaderView"
          },
          {
            "title": "Version",
            "text": "0.2.4",
            "class": "DepictionTableTextView"
          },
          {
            "title": "Developert",
            "text": "Nepeta",
            "class": "DepictionTableTextView"
          },
          {
            "title": "Compatibility",
            "text": "iOS 11 - 12.4",
            "class": "DepictionTableTextView"
          },
	
          {
            "class": "DepictionSeparatorView"
          },
          {
            "title": "Follow Me",
            "class": "DepictionHeaderView"
          },

          {
            "title": "Facebook",
            "action": "https://facebook.com.com/MrthuanJB",
            "class": "DepictionTableButtonView"
          },

          {
            "spacing": 8,
            "class": "DepictionSpacerView"
          }
        ],
        "class": "DepictionStackView"
      },
	  
	  {
        "tabname": "Changelog",
        "views": [
          {
            "title": "Version 0.2.4",
            "useBoldText": true,
            "useBottomMargin": true,
            "class": "DepictionSubheaderView"
          },
          {
            "markdown": "Stable.",
            "useSpacing": false,
            "class": "DepictionMarkdownView"
          },
          {
            "markdown": "<small style=\"color: #999; margin-top: -8px;\">Updated 20-09-2019<\/small>",
            "useRawFormat": true,
            "class": "DepictionMarkdownView"
          },
          {
            "class": "DepictionSeparatorView"
          }
          
        ],
        "class": "DepictionStackView"
      }
	  
    ],
    "class": "DepictionTabView"
  }